gdx2py/__init__.py
gdx2py/gams.py
gdx2py/gdxfile.py
gdx2py/version.py
GDX2py-2.2.0.dist-info/LICENSE
GDX2py-2.2.0.dist-info/METADATA
GDX2py-2.2.0.dist-info/WHEEL
GDX2py-2.2.0.dist-info/top_level.txt
GDX2py-2.2.0.dist-info/RECORD
