Metadata-Version: 2.1
Name: GDX2py
Version: 2.2.0
Summary: Read and write GAMS Data eXchange (GDX) files using Python
Home-page: https://github.com/ererkka/GDX2py
Author: Erkka Rinne
Author-email: erkka.rinne@vtt.fi
License: MIT
Classifier: Programming Language :: Python :: 3
Classifier: License :: OSI Approved :: MIT License
Classifier: Operating System :: OS Independent
Classifier: Topic :: Scientific/Engineering
Classifier: Intended Audience :: Developers
Classifier: Development Status :: 5 - Production/Stable
Requires-Python: >=3.8
License-File: LICENSE
Requires-Dist: gamsapi>=47
